steelthread/__init__.py
steelthread/steelthread.py
steelthread/evals/__init__.py
steelthread/evals/backend.py
steelthread/evals/default_evaluator.py
steelthread/evals/eval_runner.py
steelthread/evals/evaluator.py
steelthread/evals/metrics.py
steelthread/evals/models.py
steelthread/evals/tags.py
steelthread/portia/__init__.py
steelthread/portia/portia.py
steelthread/portia/storage.py
steelthread/portia/tools.py
steelthread/streams/__init__.py
steelthread/streams/backend.py
steelthread/streams/evaluator.py
steelthread/streams/llm_as_judge.py
steelthread/streams/metrics.py
steelthread/streams/models.py
steelthread/streams/stream_processor.py
steelthread/streams/tags.py
steelthread/utils/__init__.py
steelthread/utils/llm.py
steel_thread-0.1.19.dist-info/METADATA
steel_thread-0.1.19.dist-info/WHEEL
steel_thread-0.1.19.dist-info/licenses/LICENSE
steel_thread-0.1.19.dist-info/RECORD
