Metadata-Version: 2.4
Name: steel-thread
Version: 0.1.19
Summary: Portia Labs Eval framework for evaluating agentic workflows.
Project-URL: Homepage, https://www.portialabs.ai/
Project-URL: Repository, https://github.com/portiaAI/steel_thread
Project-URL: Documentation, https://docs.portialabs.ai
License: MIT License
License-File: LICENSE
Keywords: LLM,agentic,workflow
Classifier: Development Status :: 3 - Alpha
Requires-Python: >=3.11
Requires-Dist: httpx>=0.28.1
Requires-Dist: portia-sdk-python[all]>=0.7.2
Requires-Dist: pydantic>=2.11.7
